setup.py
khalid_dsnd_probability/Binomialdistribution.py
khalid_dsnd_probability/Gaussiandistribution.py
khalid_dsnd_probability/Generaldistribution.py
khalid_dsnd_probability/__init__.py
khalid_dsnd_probability.egg-info/PKG-INFO
khalid_dsnd_probability.egg-info/SOURCES.txt
khalid_dsnd_probability.egg-info/dependency_links.txt
khalid_dsnd_probability.egg-info/not-zip-safe
khalid_dsnd_probability.egg-info/top_level.txt