Metadata-Version: 2.1
Name: khalid-dsnd-probability
Version: 1.0
Summary: Gaussian distributions
Author: Khalid Saaydh
Author-email: Khalidw501@gmail.com
